aicorn/__init__.py
aicorn/__main__.py
aicorn/aeon/__init__.py
aicorn/client/__init__.py
aicorn/server/__init__.py
aicorn/vendor/__init__.py
aicorn/vendor/options.py
aicorn-0.0.1a0.dist-info/METADATA
aicorn-0.0.1a0.dist-info/WHEEL
aicorn-0.0.1a0.dist-info/top_level.txt
aicorn-0.0.1a0.dist-info/RECORD
