Metadata-Version: 2.1
Name: aicorn
Version: 0.0.1a0
Summary: Learning python step by step
Home-page: https://github.com/littocats/aicorn
Author: 程巍巍
Author-email: aicorn@aicorn.cn
License: UNKNOWN
Platform: UNKNOWN
Classifier: Programming Language :: Python :: 3
Classifier: Operating System :: OS Independent
Requires-Python: >=3.7
